{"name":"DPC 2023 WEU Winter Tour Division I – presented by PGL","description":"The DPC 2022-2023 Winter Tour will take place from 8 January to 21 February. This tournament will determine the teams that will play in the first major of the season.","start_date":1673164800,"end_date":1675065600,"last_activity":1673278018,"roster_lock":[{"period":"period_1","start_time":1673164800},{"period":"period_2","start_time":1673856000},{"period":"period_3","start_time":1674460800}],"schedule":[{"period":"1","team_name_1":"Team Liquid","team_name_2":"Team Secret","best_of":3,"time":1673283600},{"period":"3","team_name_1":"Team Liquid","team_name_2":"OG","best_of":3,"time":1674828000},{"period":"2","team_name_1":"Team Liquid","team_name_2":"Nigma Galaxy","best_of":3,"time":1674234000},{"period":"1","team_name_1":"Team Liquid","team_name_2":"Tundra Esports","best_of":3,"time":1673629200},{"period":"2","team_name_1":"Team Liquid","team_name_2":"ITB.Shuffle","best_of":3,"time":1674061200},{"period":"3","team_name_1":"Team Liquid","team_name_2":"Gaimin Gladiators","best_of":3,"time":1674504000},{"period":"2","team_name_1":"Team Liquid","team_name_2":"Entity","best_of":3,"time":1673888400},{"period":"1","team_name_1":"Team Secret","team_name_2":"OG","best_of":3,"time":1673445600},{"period":"3","team_name_1":"Team Secret","team_name_2":"Nigma Galaxy","best_of":3,"time":1674849600},{"period":"2","team_name_1":"Team Secret","team_name_2":"Tundra Esports","best_of":3,"time":1674244800},{"period":"3","team_name_1":"Team Secret","team_name_2":"ITB.Shuffle","best_of":3,"time":1674493200},{"period":"1","team_name_1":"Team Secret","team_name_2":"Gaimin Gladiators","best_of":3,"time":1673618400},{"period":"2","team_name_1":"Team Secret","team_name_2":"Entity","best_of":3,"time":1674050400},{"period":"3","team_name_1":"OG","team_name_2":"Nigma Galaxy","best_of":3,"time":1674655200},{"period":"1","team_name_1":"OG","team_name_2":"Tundra Esports","best_of":3,"time":1673272800},{"period":"2","team_name_1":"OG","team_name_2":"ITB.Shuffle","best_of":3,"time":1674223200},{"period":"2","team_name_1":"OG","team_name_2":"Gaimin Gladiators","best_of":3,"time":1673877600},{"period":"3","team_name_1":"OG","team_name_2":"Entity","best_of":3,"time":1674482400},{"period":"1","team_name_1":"Nigma Galaxy","team_name_2":"Tundra Esports","best_of":3,"time":1673467200},{"period":"1","team_name_1":"Nigma Galaxy","team_name_2":"ITB.Shuffle","best_of":3,"time":1673640000},{"period":"2","team_name_1":"Nigma Galaxy","team_name_2":"Gaimin Gladiators","best_of":3,"time":1674072000},{"period":"3","team_name_1":"Nigma Galaxy","team_name_2":"Entity","best_of":3,"time":1675022400},{"period":"2","team_name_1":"Tundra Esports","team_name_2":"ITB.Shuffle","best_of":3,"time":1673899200},{"period":"3","team_name_1":"Tundra Esports","team_name_2":"Gaimin Gladiators","best_of":3,"time":1674838800},{"period":"3","team_name_1":"Tundra Esports","team_name_2":"Entity","best_of":3,"time":1674676800},{"period":"3","team_name_1":"ITB.Shuffle","team_name_2":"Gaimin Gladiators","best_of":3,"time":1674666000},{"period":"1","team_name_1":"ITB.Shuffle","team_name_2":"Entity","best_of":3,"time":1673456400},{"period":"1","team_name_1":"Gaimin Gladiators","team_name_2":"Entity","best_of":3,"time":1673294400}],"result_single":[{"player_name":"Sneyking","team_name":"Tundra Esports","player_role":"Support","match_id":6961787820,"start_time":1673272881,"kills":0.6,"deaths":1.5,"creep_score":0.306,"gold_per_min":0.73,"tower_kills":0,"roshan_kills":0,"team_fight":2.1111,"obs_wards_planted":5,"camps_stacked":1.5,"runes_grabbed":1.5,"first_blood":0,"stuns":0.1137,"total":13.3608},{"player_name":"skiter","team_name":"Tundra Esports","player_role":"Core","match_id":6961787820,"start_time":1673272881,"kills":3.6,"deaths":3,"creep_score":1.449,"gold_per_min":1.55,"tower_kills":1,"roshan_kills":1,"team_fight":2.7778,"obs_wards_planted":0.5,"camps_stacked":3,"runes_grabbed":2,"first_blood":0,"stuns":1.6289,"total":21.5057},{"player_name":"Nine","team_name":"Tundra Esports","player_role":"Mid","match_id":6961787820,"start_time":1673272881,"kills":2.1,"deaths":2.1,"creep_score":1.26,"gold_per_min":1.49,"tower_kills":4,"roshan_kills":1,"team_fight":2.1111,"obs_wards_planted":0.5,"camps_stacked":0.5,"runes_grabbed":3,"first_blood":0,"stuns":1.9925,"total":20.0536},{"player_name":"33","team_name":"Tundra Esports","player_role":"Core","match_id":6961787820,"start_time":1673272881,"kills":1.2,"deaths":1.8,"creep_score":0.843,"gold_per_min":0.978,"tower_kills":5,"roshan_kills":0,"team_fight":1.4444,"obs_wards_planted":0,"camps_stacked":2,"runes_grabbed":0.75,"first_blood":0,"stuns":0.6644,"total":14.6798},{"player_name":"Saksa","team_name":"Tundra Esports","player_role":"Support","match_id":6961787820,"start_time":1673272881,"kills":0.6,"deaths":-0.3,"creep_score":0.177,"gold_per_min":0.698,"tower_kills":0,"roshan_kills":0,"team_fight":1.8889,"obs_wards_planted":4.5,"camps_stacked":0.5,"runes_grabbed":0.75,"first_blood":0,"stuns":2.12,"total":10.9339},{"player_name":"Misha","team_name":"OG","player_role":"Support","match_id":6961787820,"start_time":1673272881,"kills":0.6,"deaths":-0.3,"creep_score":0.129,"gold_per_min":0.45,"tower_kills":0,"roshan_kills":0,"team_fight":1.9565,"obs_wards_planted":3,"camps_stacked":1,"runes_grabbed":0,"first_blood":4,"stuns":2.7294,"total":13.5649},{"player_name":"bzm","team_name":"OG","player_role":"Mid","match_id":6961787820,"start_time":1673272881,"kills":2.1,"deaths":2.4,"creep_score":1.167,"gold_per_min":1.188,"tower_kills":0,"roshan_kills":1,"team_fight":1.6957,"obs_wards_planted":0.5,"camps_stacked":0.5,"runes_grabbed":2.75,"first_blood":0,"stuns":0,"total":13.3007},{"player_name":"DM","team_name":"OG","player_role":"Core","match_id":6961787820,"start_time":1673272881,"kills":0.6,"deaths":2.1,"creep_score":0.771,"gold_per_min":1.284,"tower_kills":0,"roshan_kills":0,"team_fight":1.4348,"obs_wards_planted":0,"camps_stacked":0.5,"runes_grabbed":0.75,"first_blood":0,"stuns":2.6383,"total":10.0781},{"player_name":"yuragi","team_name":"OG","player_role":"Core","match_id":6961787820,"start_time":1673272881,"kills":3.3,"deaths":1.5,"creep_score":1.44,"gold_per_min":1.338,"tower_kills":2,"roshan_kills":0,"team_fight":2.3478,"obs_wards_planted":0,"camps_stacked":3,"runes_grabbed":1.25,"first_blood":0,"stuns":1.7861,"total":17.9619},{"player_name":"Taiga","team_name":"OG","player_role":"Support","match_id":6961787820,"start_time":1673272881,"kills":0.3,"deaths":1.2,"creep_score":0.096,"gold_per_min":0.436,"tower_kills":0,"roshan_kills":0,"team_fight":3.1304,"obs_wards_planted":6.5,"camps_stacked":0.5,"runes_grabbed":0.75,"first_blood":0,"stuns":2.6552,"total":15.5676}],"result_average":[{"player_name":"Sneyking","team_name":"Tundra Esports","player_role":"Support","kills":0.6,"deaths":1.5,"creep_score":0.306,"gold_per_min":0.73,"tower_kills":0,"roshan_kills":0,"team_fight":2.1111,"obs_wards_planted":5,"camps_stacked":1.5,"runes_grabbed":1.5,"first_blood":0,"stuns":0.1137,"total":13.3608},{"player_name":"DM","team_name":"OG","player_role":"Core","kills":0.6,"deaths":2.1,"creep_score":0.771,"gold_per_min":1.284,"tower_kills":0,"roshan_kills":0,"team_fight":1.4348,"obs_wards_planted":0,"camps_stacked":0.5,"runes_grabbed":0.75,"first_blood":0,"stuns":2.6383,"total":10.0781},{"player_name":"33","team_name":"Tundra Esports","player_role":"Core","kills":1.2,"deaths":1.8,"creep_score":0.843,"gold_per_min":0.978,"tower_kills":5,"roshan_kills":0,"team_fight":1.4444,"obs_wards_planted":0,"camps_stacked":2,"runes_grabbed":0.75,"first_blood":0,"stuns":0.6644,"total":14.6798},{"player_name":"Misha","team_name":"OG","player_role":"Support","kills":0.6,"deaths":-0.3,"creep_score":0.129,"gold_per_min":0.45,"tower_kills":0,"roshan_kills":0,"team_fight":1.9565,"obs_wards_planted":3,"camps_stacked":1,"runes_grabbed":0,"first_blood":4,"stuns":2.7294,"total":13.5649},{"player_name":"bzm","team_name":"OG","player_role":"Mid","kills":2.1,"deaths":2.4,"creep_score":1.167,"gold_per_min":1.188,"tower_kills":0,"roshan_kills":1,"team_fight":1.6957,"obs_wards_planted":0.5,"camps_stacked":0.5,"runes_grabbed":2.75,"first_blood":0,"stuns":0,"total":13.3007},{"player_name":"Nine","team_name":"Tundra Esports","player_role":"Mid","kills":2.1,"deaths":2.1,"creep_score":1.26,"gold_per_min":1.49,"tower_kills":4,"roshan_kills":1,"team_fight":2.1111,"obs_wards_planted":0.5,"camps_stacked":0.5,"runes_grabbed":3,"first_blood":0,"stuns":1.9925,"total":20.0536},{"player_name":"skiter","team_name":"Tundra Esports","player_role":"Core","kills":3.6,"deaths":3,"creep_score":1.449,"gold_per_min":1.55,"tower_kills":1,"roshan_kills":1,"team_fight":2.7778,"obs_wards_planted":0.5,"camps_stacked":3,"runes_grabbed":2,"first_blood":0,"stuns":1.6289,"total":21.5057},{"player_name":"Saksa","team_name":"Tundra Esports","player_role":"Support","kills":0.6,"deaths":-0.3,"creep_score":0.177,"gold_per_min":0.698,"tower_kills":0,"roshan_kills":0,"team_fight":1.8889,"obs_wards_planted":4.5,"camps_stacked":0.5,"runes_grabbed":0.75,"first_blood":0,"stuns":2.12,"total":10.9339},{"player_name":"yuragi","team_name":"OG","player_role":"Core","kills":3.3,"deaths":1.5,"creep_score":1.44,"gold_per_min":1.338,"tower_kills":2,"roshan_kills":0,"team_fight":2.3478,"obs_wards_planted":0,"camps_stacked":3,"runes_grabbed":1.25,"first_blood":0,"stuns":1.7861,"total":17.9619},{"player_name":"Taiga","team_name":"OG","player_role":"Support","kills":0.3,"deaths":1.2,"creep_score":0.096,"gold_per_min":0.436,"tower_kills":0,"roshan_kills":0,"team_fight":3.1304,"obs_wards_planted":6.5,"camps_stacked":0.5,"runes_grabbed":0.75,"first_blood":0,"stuns":2.6552,"total":15.5676},{"player_name":"tOfu","team_name":"Gaimin Gladiators","player_role":"Support","kills":"NA","deaths":"NA","creep_score":"NA","gold_per_min":"NA","tower_kills":"NA","roshan_kills":"NA","team_fight":"NA","obs_wards_planted":"NA","camps_stacked":"NA","runes_grabbed":"NA","first_blood":"NA","stuns":"NA","total":"NA"},{"player_name":"mc","team_name":"Nigma Galaxy","player_role":"Core","kills":"NA","deaths":"NA","creep_score":"NA","gold_per_min":"NA","tower_kills":"NA","roshan_kills":"NA","team_fight":"NA","obs_wards_planted":"NA","camps_stacked":"NA","runes_grabbed":"NA","first_blood":"NA","stuns":"NA","total":"NA"},{"player_name":"Xibbe","team_name":"ITB.Shuffle","player_role":"Core","kills":"NA","deaths":"NA","creep_score":"NA","gold_per_min":"NA","tower_kills":"NA","roshan_kills":"NA","team_fight":"NA","obs_wards_planted":"NA","camps_stacked":"NA","runes_grabbed":"NA","first_blood":"NA","stuns":"NA","total":"NA"},{"player_name":"Insania","team_name":"Team Liquid","player_role":"Support","kills":"NA","deaths":"NA","creep_score":"NA","gold_per_min":"NA","tower_kills":"NA","roshan_kills":"NA","team_fight":"NA","obs_wards_planted":"NA","camps_stacked":"NA","runes_grabbed":"NA","first_blood":"NA","stuns":"NA","total":"NA"},{"player_name":"Supream^","team_name":"ITB.Shuffle","player_role":"Mid","kills":"NA","deaths":"NA","creep_score":"NA","gold_per_min":"NA","tower_kills":"NA","roshan_kills":"NA","team_fight":"NA","obs_wards_planted":"NA","camps_stacked":"NA","runes_grabbed":"NA","first_blood":"NA","stuns":"NA","total":"NA"},{"player_name":"zai","team_name":"Team Liquid","player_role":"Core","kills":"NA","deaths":"NA","creep_score":"NA","gold_per_min":"NA","tower_kills":"NA","roshan_kills":"NA","team_fight":"NA","obs_wards_planted":"NA","camps_stacked":"NA","runes_grabbed":"NA","first_blood":"NA","stuns":"NA","total":"NA"},{"player_name":"Boxi","team_name":"Team Liquid","player_role":"Support","kills":"NA","deaths":"NA","creep_score":"NA","gold_per_min":"NA","tower_kills":"NA","roshan_kills":"NA","team_fight":"NA","obs_wards_planted":"NA","camps_stacked":"NA","runes_grabbed":"NA","first_blood":"NA","stuns":"NA","total":"NA"},{"player_name":"KuroKy","team_name":"Nigma Galaxy","player_role":"Support","kills":"NA","deaths":"NA","creep_score":"NA","gold_per_min":"NA","tower_kills":"NA","roshan_kills":"NA","team_fight":"NA","obs_wards_planted":"NA","camps_stacked":"NA","runes_grabbed":"NA","first_blood":"NA","stuns":"NA","total":"NA"},{"player_name":"Resolut1on","team_name":"Team Secret","player_role":"Core","kills":"NA","deaths":"NA","creep_score":"NA","gold_per_min":"NA","tower_kills":"NA","roshan_kills":"NA","team_fight":"NA","obs_wards_planted":"NA","camps_stacked":"NA","runes_grabbed":"NA","first_blood":"NA","stuns":"NA","total":"NA"},{"player_name":"Puppey","team_name":"Team Secret","player_role":"Support","kills":"NA","deaths":"NA","creep_score":"NA","gold_per_min":"NA","tower_kills":"NA","roshan_kills":"NA","team_fight":"NA","obs_wards_planted":"NA","camps_stacked":"NA","runes_grabbed":"NA","first_blood":"NA","stuns":"NA","total":"NA"},{"player_name":"Seleri","team_name":"Gaimin Gladiators","player_role":"Support","kills":"NA","deaths":"NA","creep_score":"NA","gold_per_min":"NA","tower_kills":"NA","roshan_kills":"NA","team_fight":"NA","obs_wards_planted":"NA","camps_stacked":"NA","runes_grabbed":"NA","first_blood":"NA","stuns":"NA","total":"NA"},{"player_name":"Stormstormer","team_name":"Entity","player_role":"Mid","kills":"NA","deaths":"NA","creep_score":"NA","gold_per_min":"NA","tower_kills":"NA","roshan_kills":"NA","team_fight":"NA","obs_wards_planted":"NA","camps_stacked":"NA","runes_grabbed":"NA","first_blood":"NA","stuns":"NA","total":"NA"},{"player_name":"Ace ♠","team_name":"Gaimin Gladiators","player_role":"Core","kills":"NA","deaths":"NA","creep_score":"NA","gold_per_min":"NA","tower_kills":"NA","roshan_kills":"NA","team_fight":"NA","obs_wards_planted":"NA","camps_stacked":"NA","runes_grabbed":"NA","first_blood":"NA","stuns":"NA","total":"NA"},{"player_name":"GH","team_name":"Nigma Galaxy","player_role":"Support","kills":"NA","deaths":"NA","creep_score":"NA","gold_per_min":"NA","tower_kills":"NA","roshan_kills":"NA","team_fight":"NA","obs_wards_planted":"NA","camps_stacked":"NA","runes_grabbed":"NA","first_blood":"NA","stuns":"NA","total":"NA"},{"player_name":"Kidaro","team_name":"ITB.Shuffle","player_role":"Support","kills":"NA","deaths":"NA","creep_score":"NA","gold_per_min":"NA","tower_kills":"NA","roshan_kills":"NA","team_fight":"NA","obs_wards_planted":"NA","camps_stacked":"NA","runes_grabbed":"NA","first_blood":"NA","stuns":"NA","total":"NA"},{"player_name":"W_Zayac","team_name":"Team Secret","player_role":"Support","kills":"NA","deaths":"NA","creep_score":"NA","gold_per_min":"NA","tower_kills":"NA","roshan_kills":"NA","team_fight":"NA","obs_wards_planted":"NA","camps_stacked":"NA","runes_grabbed":"NA","first_blood":"NA","stuns":"NA","total":"NA"},{"player_name":"Suma1L-","team_name":"Nigma Galaxy","player_role":"Mid","kills":"NA","deaths":"NA","creep_score":"NA","gold_per_min":"NA","tower_kills":"NA","roshan_kills":"NA","team_fight":"NA","obs_wards_planted":"NA","camps_stacked":"NA","runes_grabbed":"NA","first_blood":"NA","stuns":"NA","total":"NA"},{"player_name":"dyrachyo","team_name":"Gaimin Gladiators","player_role":"Core","kills":"NA","deaths":"NA","creep_score":"NA","gold_per_min":"NA","tower_kills":"NA","roshan_kills":"NA","team_fight":"NA","obs_wards_planted":"NA","camps_stacked":"NA","runes_grabbed":"NA","first_blood":"NA","stuns":"NA","total":"NA"},{"player_name":"Fishman","team_name":"Entity","player_role":"Support","kills":"NA","deaths":"NA","creep_score":"NA","gold_per_min":"NA","tower_kills":"NA","roshan_kills":"NA","team_fight":"NA","obs_wards_planted":"NA","camps_stacked":"NA","runes_grabbed":"NA","first_blood":"NA","stuns":"NA","total":"NA"},{"player_name":"Crystallis","team_name":"Team Secret","player_role":"Core","kills":"NA","deaths":"NA","creep_score":"NA","gold_per_min":"NA","tower_kills":"NA","roshan_kills":"NA","team_fight":"NA","obs_wards_planted":"NA","camps_stacked":"NA","runes_grabbed":"NA","first_blood":"NA","stuns":"NA","total":"NA"},{"player_name":"Tobi","team_name":"Entity","player_role":"Core","kills":"NA","deaths":"NA","creep_score":"NA","gold_per_min":"NA","tower_kills":"NA","roshan_kills":"NA","team_fight":"NA","obs_wards_planted":"NA","camps_stacked":"NA","runes_grabbed":"NA","first_blood":"NA","stuns":"NA","total":"NA"},{"player_name":"m1CKe","team_name":"Team Liquid","player_role":"Mid","kills":"NA","deaths":"NA","creep_score":"NA","gold_per_min":"NA","tower_kills":"NA","roshan_kills":"NA","team_fight":"NA","obs_wards_planted":"NA","camps_stacked":"NA","runes_grabbed":"NA","first_blood":"NA","stuns":"NA","total":"NA"},{"player_name":"医者watson`","team_name":"Entity","player_role":"Core","kills":"NA","deaths":"NA","creep_score":"NA","gold_per_min":"NA","tower_kills":"NA","roshan_kills":"NA","team_fight":"NA","obs_wards_planted":"NA","camps_stacked":"NA","runes_grabbed":"NA","first_blood":"NA","stuns":"NA","total":"NA"},{"player_name":"AMMAR_THE_F","team_name":"Nigma Galaxy","player_role":"Core","kills":"NA","deaths":"NA","creep_score":"NA","gold_per_min":"NA","tower_kills":"NA","roshan_kills":"NA","team_fight":"NA","obs_wards_planted":"NA","camps_stacked":"NA","runes_grabbed":"NA","first_blood":"NA","stuns":"NA","total":"NA"},{"player_name":"BOOM","team_name":"Team Secret","player_role":"Mid","kills":"NA","deaths":"NA","creep_score":"NA","gold_per_min":"NA","tower_kills":"NA","roshan_kills":"NA","team_fight":"NA","obs_wards_planted":"NA","camps_stacked":"NA","runes_grabbed":"NA","first_blood":"NA","stuns":"NA","total":"NA"},{"player_name":"Otaker","team_name":"ITB.Shuffle","player_role":"Core","kills":"NA","deaths":"NA","creep_score":"NA","gold_per_min":"NA","tower_kills":"NA","roshan_kills":"NA","team_fight":"NA","obs_wards_planted":"NA","camps_stacked":"NA","runes_grabbed":"NA","first_blood":"NA","stuns":"NA","total":"NA"},{"player_name":"Kataomi`","team_name":"Entity","player_role":"Support","kills":"NA","deaths":"NA","creep_score":"NA","gold_per_min":"NA","tower_kills":"NA","roshan_kills":"NA","team_fight":"NA","obs_wards_planted":"NA","camps_stacked":"NA","runes_grabbed":"NA","first_blood":"NA","stuns":"NA","total":"NA"},{"player_name":"Nisha","team_name":"Team Liquid","player_role":"Core","kills":"NA","deaths":"NA","creep_score":"NA","gold_per_min":"NA","tower_kills":"NA","roshan_kills":"NA","team_fight":"NA","obs_wards_planted":"NA","camps_stacked":"NA","runes_grabbed":"NA","first_blood":"NA","stuns":"NA","total":"NA"},{"player_name":"Quinn","team_name":"Gaimin Gladiators","player_role":"Mid","kills":"NA","deaths":"NA","creep_score":"NA","gold_per_min":"NA","tower_kills":"NA","roshan_kills":"NA","team_fight":"NA","obs_wards_planted":"NA","camps_stacked":"NA","runes_grabbed":"NA","first_blood":"NA","stuns":"NA","total":"NA"},{"player_name":"Immersion","team_name":"ITB.Shuffle","player_role":"Support","kills":"NA","deaths":"NA","creep_score":"NA","gold_per_min":"NA","tower_kills":"NA","roshan_kills":"NA","team_fight":"NA","obs_wards_planted":"NA","camps_stacked":"NA","runes_grabbed":"NA","first_blood":"NA","stuns":"NA","total":"NA"}],"result_aggregate":[{"player_name":"Sneyking","team_name":"Tundra Esports","player_role":"Support","1":13.3608,"NA":"NA","total":13.3608},{"player_name":"DM","team_name":"OG","player_role":"Core","1":10.0781,"NA":"NA","total":10.0781},{"player_name":"33","team_name":"Tundra Esports","player_role":"Core","1":14.6798,"NA":"NA","total":14.6798},{"player_name":"Misha","team_name":"OG","player_role":"Support","1":13.5649,"NA":"NA","total":13.5649},{"player_name":"bzm","team_name":"OG","player_role":"Mid","1":13.3007,"NA":"NA","total":13.3007},{"player_name":"Nine","team_name":"Tundra Esports","player_role":"Mid","1":20.0536,"NA":"NA","total":20.0536},{"player_name":"skiter","team_name":"Tundra Esports","player_role":"Core","1":21.5057,"NA":"NA","total":21.5057},{"player_name":"Saksa","team_name":"Tundra Esports","player_role":"Support","1":10.9339,"NA":"NA","total":10.9339},{"player_name":"yuragi","team_name":"OG","player_role":"Core","1":17.9619,"NA":"NA","total":17.9619},{"player_name":"Taiga","team_name":"OG","player_role":"Support","1":15.5676,"NA":"NA","total":15.5676},{"player_name":"tOfu","team_name":"Gaimin Gladiators","player_role":"Support","1":"NA","NA":"NA","total":0},{"player_name":"mc","team_name":"Nigma Galaxy","player_role":"Core","1":"NA","NA":"NA","total":0},{"player_name":"Xibbe","team_name":"ITB.Shuffle","player_role":"Core","1":"NA","NA":"NA","total":0},{"player_name":"Insania","team_name":"Team Liquid","player_role":"Support","1":"NA","NA":"NA","total":0},{"player_name":"Supream^","team_name":"ITB.Shuffle","player_role":"Mid","1":"NA","NA":"NA","total":0},{"player_name":"zai","team_name":"Team Liquid","player_role":"Core","1":"NA","NA":"NA","total":0},{"player_name":"Boxi","team_name":"Team Liquid","player_role":"Support","1":"NA","NA":"NA","total":0},{"player_name":"KuroKy","team_name":"Nigma Galaxy","player_role":"Support","1":"NA","NA":"NA","total":0},{"player_name":"Resolut1on","team_name":"Team Secret","player_role":"Core","1":"NA","NA":"NA","total":0},{"player_name":"Puppey","team_name":"Team Secret","player_role":"Support","1":"NA","NA":"NA","total":0},{"player_name":"Seleri","team_name":"Gaimin Gladiators","player_role":"Support","1":"NA","NA":"NA","total":0},{"player_name":"Stormstormer","team_name":"Entity","player_role":"Mid","1":"NA","NA":"NA","total":0},{"player_name":"Ace ♠","team_name":"Gaimin Gladiators","player_role":"Core","1":"NA","NA":"NA","total":0},{"player_name":"GH","team_name":"Nigma Galaxy","player_role":"Support","1":"NA","NA":"NA","total":0},{"player_name":"Kidaro","team_name":"ITB.Shuffle","player_role":"Support","1":"NA","NA":"NA","total":0},{"player_name":"W_Zayac","team_name":"Team Secret","player_role":"Support","1":"NA","NA":"NA","total":0},{"player_name":"Suma1L-","team_name":"Nigma Galaxy","player_role":"Mid","1":"NA","NA":"NA","total":0},{"player_name":"dyrachyo","team_name":"Gaimin Gladiators","player_role":"Core","1":"NA","NA":"NA","total":0},{"player_name":"Fishman","team_name":"Entity","player_role":"Support","1":"NA","NA":"NA","total":0},{"player_name":"Crystallis","team_name":"Team Secret","player_role":"Core","1":"NA","NA":"NA","total":0},{"player_name":"Tobi","team_name":"Entity","player_role":"Core","1":"NA","NA":"NA","total":0},{"player_name":"m1CKe","team_name":"Team Liquid","player_role":"Mid","1":"NA","NA":"NA","total":0},{"player_name":"医者watson`","team_name":"Entity","player_role":"Core","1":"NA","NA":"NA","total":0},{"player_name":"AMMAR_THE_F","team_name":"Nigma Galaxy","player_role":"Core","1":"NA","NA":"NA","total":0},{"player_name":"BOOM","team_name":"Team Secret","player_role":"Mid","1":"NA","NA":"NA","total":0},{"player_name":"Otaker","team_name":"ITB.Shuffle","player_role":"Core","1":"NA","NA":"NA","total":0},{"player_name":"Kataomi`","team_name":"Entity","player_role":"Support","1":"NA","NA":"NA","total":0},{"player_name":"Nisha","team_name":"Team Liquid","player_role":"Core","1":"NA","NA":"NA","total":0},{"player_name":"Quinn","team_name":"Gaimin Gladiators","player_role":"Mid","1":"NA","NA":"NA","total":0},{"player_name":"Immersion","team_name":"ITB.Shuffle","player_role":"Support","1":"NA","NA":"NA","total":0}]}
