{"name":"DPC 2023 EEU Spring Tour Division I - presented by Paragon Events","description":"The eight best teams from the EEU region will play against each other for the essential DPC points, Major slots, and the opportunity to qualify directly to the International 2023.","start_date":1678320000,"end_date":1680825600,"last_activity":1678807222,"roster_lock":[{"period":"period_1","start_time":1678608000},{"period":"period_2","start_time":1679212800},{"period":"period_3","start_time":1679817600}],"schedule":[{"period":"2","team_name_1":"Natus Vincere","team_name_2":"Team Spirit","best_of":3,"time":1679742000},{"period":"3","team_name_1":"Natus Vincere","team_name_2":"HellRaisers","best_of":3,"time":1680174000},{"period":"1","team_name_1":"Natus Vincere","team_name_2":"BetBoom Team","best_of":3,"time":1678975200},{"period":"3","team_name_1":"Natus Vincere","team_name_2":"One Move","best_of":3,"time":1680012000},{"period":"1","team_name_1":"Natus Vincere","team_name_2":"HYDRA","best_of":3,"time":1679158800},{"period":"3","team_name_1":"Natus Vincere","team_name_2":"Virtus.pro","best_of":3,"time":1680444000},{"period":"1","team_name_1":"Natus Vincere","team_name_2":"Darkside","best_of":3,"time":1678618800},{"period":"3","team_name_1":"Team Spirit","team_name_2":"HellRaisers","best_of":3,"time":1680368400},{"period":"1","team_name_1":"Team Spirit","team_name_2":"BetBoom Team","best_of":3,"time":1679148000},{"period":"1","team_name_1":"Team Spirit","team_name_2":"One Move","best_of":3,"time":1678791600},{"period":"2","team_name_1":"Team Spirit","team_name_2":"HYDRA","best_of":3,"time":1679407200},{"period":"3","team_name_1":"Team Spirit","team_name_2":"Virtus.pro","best_of":3,"time":1680184800},{"period":"3","team_name_1":"Team Spirit","team_name_2":"Darkside","best_of":3,"time":1679839200},{"period":"2","team_name_1":"HellRaisers","team_name_2":"BetBoom Team","best_of":3,"time":1679580000},{"period":"1","team_name_1":"HellRaisers","team_name_2":"One Move","best_of":3,"time":1679137200},{"period":"2","team_name_1":"HellRaisers","team_name_2":"HYDRA","best_of":3,"time":1679752800},{"period":"1","team_name_1":"HellRaisers","team_name_2":"Virtus.pro","best_of":3,"time":1678802400},{"period":"2","team_name_1":"HellRaisers","team_name_2":"Darkside","best_of":3,"time":1679234400},{"period":"2","team_name_1":"BetBoom Team","team_name_2":"One Move","best_of":3,"time":1679396400},{"period":"3","team_name_1":"BetBoom Team","team_name_2":"HYDRA","best_of":3,"time":1679828400},{"period":"3","team_name_1":"BetBoom Team","team_name_2":"Virtus.pro","best_of":3,"time":1680001200},{"period":"3","team_name_1":"BetBoom Team","team_name_2":"Darkside","best_of":3,"time":1680454800},{"period":"1","team_name_1":"One Move","team_name_2":"HYDRA","best_of":3,"time":1678629600},{"period":"2","team_name_1":"One Move","team_name_2":"Virtus.pro","best_of":3,"time":1679763600},{"period":"3","team_name_1":"One Move","team_name_2":"Darkside","best_of":3,"time":1680357600},{"period":"3","team_name_1":"HYDRA","team_name_2":"Virtus.pro","best_of":3,"time":1680346800},{"period":"1","team_name_1":"HYDRA","team_name_2":"Darkside","best_of":3,"time":1678964400},{"period":"2","team_name_1":"Virtus.pro","team_name_2":"Darkside","best_of":3,"time":1679569200}],"result_single":[{"player_name":"SoNNeikO","team_name":"Darkside","player_role":"Support","match_id":7056881148,"start_time":1678618891,"kills":0.9,"deaths":0.9,"creep_score":0.159,"gold_per_min":0.462,"tower_kills":0,"roshan_kills":0,"team_fight":2.625,"obs_wards_planted":6.5,"camps_stacked":3.5,"runes_grabbed":2.25,"first_blood":0,"stuns":0,"total":17.296},{"player_name":"reibl","team_name":"Darkside","player_role":"Mid","match_id":7056881148,"start_time":1678618891,"kills":0.9,"deaths":1.2,"creep_score":1.041,"gold_per_min":1.142,"tower_kills":2,"roshan_kills":0,"team_fight":1.875,"obs_wards_planted":1,"camps_stacked":1,"runes_grabbed":0.75,"first_blood":0,"stuns":3.1883,"total":14.0963},{"player_name":"dizzying","team_name":"Darkside","player_role":"Core","match_id":7056881148,"start_time":1678618891,"kills":0.3,"deaths":0.6,"creep_score":0.966,"gold_per_min":0.906,"tower_kills":1,"roshan_kills":0,"team_fight":1.875,"obs_wards_planted":0,"camps_stacked":0,"runes_grabbed":0.25,"first_blood":0,"stuns":1.3767,"total":7.2737},{"player_name":"Blizzy","team_name":"Darkside","player_role":"Core","match_id":7056881148,"start_time":1678618891,"kills":0.3,"deaths":1.8,"creep_score":0.87,"gold_per_min":0.856,"tower_kills":0,"roshan_kills":0,"team_fight":1.875,"obs_wards_planted":0,"camps_stacked":1,"runes_grabbed":0.75,"first_blood":0,"stuns":1.1733,"total":8.6243},{"player_name":"RodjER","team_name":"Darkside","player_role":"Support","match_id":7056881148,"start_time":1678618891,"kills":0,"deaths":1.5,"creep_score":0.117,"gold_per_min":0.388,"tower_kills":0,"roshan_kills":0,"team_fight":1.5,"obs_wards_planted":2,"camps_stacked":1,"runes_grabbed":0.5,"first_blood":0,"stuns":3.0783,"total":10.0833},{"player_name":"Malady","team_name":"Natus Vincere","player_role":"Support","match_id":7056881148,"start_time":1678618891,"kills":0.6,"deaths":2.4,"creep_score":0.075,"gold_per_min":0.572,"tower_kills":0,"roshan_kills":0,"team_fight":2.1,"obs_wards_planted":4,"camps_stacked":3,"runes_grabbed":1.25,"first_blood":0,"stuns":0,"total":13.997},{"player_name":"shigetsu","team_name":"Natus Vincere","player_role":"Core","match_id":7056881148,"start_time":1678618891,"kills":4.2,"deaths":2.7,"creep_score":1.449,"gold_per_min":1.558,"tower_kills":2,"roshan_kills":2,"team_fight":1.9,"obs_wards_planted":0.5,"camps_stacked":0,"runes_grabbed":2,"first_blood":0,"stuns":1.8336,"total":20.1406},{"player_name":"mellojul","team_name":"Natus Vincere","player_role":"Mid","match_id":7056881148,"start_time":1678618891,"kills":0.9,"deaths":2.4,"creep_score":1.74,"gold_per_min":1.62,"tower_kills":4,"roshan_kills":0,"team_fight":1.5,"obs_wards_planted":0.5,"camps_stacked":2,"runes_grabbed":3.25,"first_blood":0,"stuns":1.1533,"total":19.0633},{"player_name":"Danial","team_name":"Natus Vincere","player_role":"Support","match_id":7056881148,"start_time":1678618891,"kills":2.1,"deaths":2.1,"creep_score":0.042,"gold_per_min":0.62,"tower_kills":0,"roshan_kills":0,"team_fight":2.1,"obs_wards_planted":5,"camps_stacked":0,"runes_grabbed":1.25,"first_blood":0,"stuns":0,"total":13.212},{"player_name":"Malik","team_name":"Natus Vincere","player_role":"Core","match_id":7056881148,"start_time":1678618891,"kills":1.2,"deaths":3,"creep_score":0.978,"gold_per_min":1.156,"tower_kills":2,"roshan_kills":0,"team_fight":2.2,"obs_wards_planted":0.5,"camps_stacked":0.5,"runes_grabbed":1.25,"first_blood":4,"stuns":2.32,"total":19.104},{"player_name":"Malady","team_name":"Natus Vincere","player_role":"Support","match_id":7057000328,"start_time":1678623148,"kills":0,"deaths":0.9,"creep_score":0.06,"gold_per_min":0.338,"tower_kills":0,"roshan_kills":0,"team_fight":1.2857,"obs_wards_planted":4.5,"camps_stacked":0.5,"runes_grabbed":1,"first_blood":0,"stuns":0,"total":8.5837},{"player_name":"mellojul","team_name":"Natus Vincere","player_role":"Mid","match_id":7057000328,"start_time":1678623148,"kills":0.6,"deaths":1.8,"creep_score":1.026,"gold_per_min":1.052,"tower_kills":0,"roshan_kills":0,"team_fight":2.4286,"obs_wards_planted":1,"camps_stacked":0,"runes_grabbed":1.5,"first_blood":0,"stuns":1.9917,"total":11.3983},{"player_name":"shigetsu","team_name":"Natus Vincere","player_role":"Core","match_id":7057000328,"start_time":1678623148,"kills":1.8,"deaths":1.5,"creep_score":2.07,"gold_per_min":1.606,"tower_kills":2,"roshan_kills":0,"team_fight":1.7143,"obs_wards_planted":0.5,"camps_stacked":0.5,"runes_grabbed":1,"first_blood":0,"stuns":0.955,"total":13.6453},{"player_name":"Danial","team_name":"Natus Vincere","player_role":"Support","match_id":7057000328,"start_time":1678623148,"kills":2.4,"deaths":1.5,"creep_score":0.135,"gold_per_min":0.492,"tower_kills":0,"roshan_kills":0,"team_fight":2.1429,"obs_wards_planted":5.5,"camps_stacked":0.5,"runes_grabbed":0,"first_blood":0,"stuns":0,"total":12.6699},{"player_name":"Malik","team_name":"Natus Vincere","player_role":"Core","match_id":7057000328,"start_time":1678623148,"kills":1.5,"deaths":0.3,"creep_score":1.038,"gold_per_min":0.966,"tower_kills":1,"roshan_kills":0,"team_fight":1.4286,"obs_wards_planted":0,"camps_stacked":1.5,"runes_grabbed":0.75,"first_blood":4,"stuns":0.8433,"total":13.3259},{"player_name":"SoNNeikO","team_name":"Darkside","player_role":"Support","match_id":7057000328,"start_time":1678623148,"kills":0,"deaths":1.2,"creep_score":0.144,"gold_per_min":0.64,"tower_kills":0,"roshan_kills":0,"team_fight":1.9,"obs_wards_planted":5.5,"camps_stacked":4,"runes_grabbed":2.25,"first_blood":0,"stuns":1.435,"total":17.069},{"player_name":"dizzying","team_name":"Darkside","player_role":"Core","match_id":7057000328,"start_time":1678623148,"kills":2.7,"deaths":1.8,"creep_score":1.308,"gold_per_min":1.336,"tower_kills":2,"roshan_kills":3,"team_fight":2.1,"obs_wards_planted":0.5,"camps_stacked":0.5,"runes_grabbed":2,"first_blood":0,"stuns":0.8101,"total":18.0541},{"player_name":"Blizzy","team_name":"Darkside","player_role":"Core","match_id":7057000328,"start_time":1678623148,"kills":0.9,"deaths":1.2,"creep_score":0.975,"gold_per_min":1.036,"tower_kills":2,"roshan_kills":0,"team_fight":2.5,"obs_wards_planted":0,"camps_stacked":3.5,"runes_grabbed":0.5,"first_blood":0,"stuns":1.3433,"total":13.9543},{"player_name":"reibl","team_name":"Darkside","player_role":"Mid","match_id":7057000328,"start_time":1678623148,"kills":4.8,"deaths":2.4,"creep_score":1.785,"gold_per_min":1.682,"tower_kills":5,"roshan_kills":1,"team_fight":2.6,"obs_wards_planted":0.5,"camps_stacked":0.5,"runes_grabbed":4.75,"first_blood":0,"stuns":2.1917,"total":27.2087},{"player_name":"RodjER","team_name":"Darkside","player_role":"Support","match_id":7057000328,"start_time":1678623148,"kills":0.6,"deaths":2.1,"creep_score":0.264,"gold_per_min":0.666,"tower_kills":0,"roshan_kills":0,"team_fight":2.1,"obs_wards_planted":5.5,"camps_stacked":2,"runes_grabbed":1.25,"first_blood":0,"stuns":1.5034,"total":15.9833},{"player_name":"shigetsu","team_name":"Natus Vincere","player_role":"Core","match_id":7057147873,"start_time":1678627802,"kills":3.6,"deaths":2.4,"creep_score":1.644,"gold_per_min":1.63,"tower_kills":2,"roshan_kills":2,"team_fight":2.3823,"obs_wards_planted":0,"camps_stacked":0.5,"runes_grabbed":0.5,"first_blood":0,"stuns":0.795,"total":17.4514},{"player_name":"mellojul","team_name":"Natus Vincere","player_role":"Mid","match_id":7057147873,"start_time":1678627802,"kills":0.9,"deaths":2.4,"creep_score":1.158,"gold_per_min":1.22,"tower_kills":1,"roshan_kills":0,"team_fight":1.8529,"obs_wards_planted":0.5,"camps_stacked":0.5,"runes_grabbed":3,"first_blood":0,"stuns":2.2208,"total":14.7518},{"player_name":"Malady","team_name":"Natus Vincere","player_role":"Support","match_id":7057147873,"start_time":1678627802,"kills":0.3,"deaths":1.2,"creep_score":0.12,"gold_per_min":0.524,"tower_kills":0,"roshan_kills":0,"team_fight":1.9412,"obs_wards_planted":4.5,"camps_stacked":1,"runes_grabbed":1.5,"first_blood":0,"stuns":0,"total":11.0852},{"player_name":"Danial","team_name":"Natus Vincere","player_role":"Support","match_id":7057147873,"start_time":1678627802,"kills":3.6,"deaths":1.5,"creep_score":0.324,"gold_per_min":0.778,"tower_kills":1,"roshan_kills":0,"team_fight":2.4706,"obs_wards_planted":4.5,"camps_stacked":1.5,"runes_grabbed":1,"first_blood":0,"stuns":0.5111,"total":17.1837},{"player_name":"Malik","team_name":"Natus Vincere","player_role":"Core","match_id":7057147873,"start_time":1678627802,"kills":1.5,"deaths":1.8,"creep_score":1.428,"gold_per_min":1.454,"tower_kills":4,"roshan_kills":0,"team_fight":2.1176,"obs_wards_planted":0.5,"camps_stacked":3.5,"runes_grabbed":1.75,"first_blood":0,"stuns":2.3967,"total":20.4463},{"player_name":"SoNNeikO","team_name":"Darkside","player_role":"Support","match_id":7057147873,"start_time":1678627802,"kills":0.9,"deaths":0,"creep_score":0.213,"gold_per_min":0.488,"tower_kills":0,"roshan_kills":0,"team_fight":2.3684,"obs_wards_planted":3.5,"camps_stacked":1.5,"runes_grabbed":1.5,"first_blood":0,"stuns":2.5133,"total":12.9827},{"player_name":"dizzying","team_name":"Darkside","player_role":"Core","match_id":7057147873,"start_time":1678627802,"kills":2.7,"deaths":1.5,"creep_score":1.143,"gold_per_min":1.184,"tower_kills":1,"roshan_kills":0,"team_fight":2.0526,"obs_wards_planted":0,"camps_stacked":1.5,"runes_grabbed":0.5,"first_blood":4,"stuns":0.0083,"total":15.588},{"player_name":"Blizzy","team_name":"Darkside","player_role":"Core","match_id":7057147873,"start_time":1678627802,"kills":0.3,"deaths":0.9,"creep_score":1.008,"gold_per_min":0.956,"tower_kills":2,"roshan_kills":1,"team_fight":1.8947,"obs_wards_planted":0,"camps_stacked":1.5,"runes_grabbed":0.5,"first_blood":0,"stuns":4.9734,"total":15.0322},{"player_name":"reibl","team_name":"Darkside","player_role":"Mid","match_id":7057147873,"start_time":1678627802,"kills":1.2,"deaths":0.9,"creep_score":1.056,"gold_per_min":1.066,"tower_kills":1,"roshan_kills":0,"team_fight":2.0526,"obs_wards_planted":1,"camps_stacked":1,"runes_grabbed":2.75,"first_blood":0,"stuns":1.17,"total":13.1946},{"player_name":"RodjER","team_name":"Darkside","player_role":"Support","match_id":7057147873,"start_time":1678627802,"kills":0.6,"deaths":1.2,"creep_score":0.252,"gold_per_min":0.512,"tower_kills":0,"roshan_kills":0,"team_fight":2.6842,"obs_wards_planted":5,"camps_stacked":0.5,"runes_grabbed":0,"first_blood":0,"stuns":6.41,"total":17.1582},{"player_name":"Munkushi~太阳","team_name":"One Move","player_role":"Core","match_id":7057305063,"start_time":1678632306,"kills":4.5,"deaths":1.8,"creep_score":3.123,"gold_per_min":2.066,"tower_kills":6,"roshan_kills":1,"team_fight":2.3415,"obs_wards_planted":0.5,"camps_stacked":1.5,"runes_grabbed":0.5,"first_blood":0,"stuns":5.5451,"total":28.8756},{"player_name":"Ainkrad","team_name":"One Move","player_role":"Mid","match_id":7057305063,"start_time":1678632306,"kills":4.8,"deaths":-0.3,"creep_score":1.146,"gold_per_min":1.232,"tower_kills":1,"roshan_kills":1,"team_fight":2.561,"obs_wards_planted":1,"camps_stacked":0,"runes_grabbed":3,"first_blood":0,"stuns":4.7051,"total":20.1441},{"player_name":"pantomem","team_name":"One Move","player_role":"Support","match_id":7057305063,"start_time":1678632306,"kills":0.9,"deaths":-0.9,"creep_score":0.105,"gold_per_min":0.6,"tower_kills":0,"roshan_kills":0,"team_fight":1.6829,"obs_wards_planted":7.5,"camps_stacked":0,"runes_grabbed":1.25,"first_blood":0,"stuns":1.2567,"total":12.3946},{"player_name":"Gilgir","team_name":"One Move","player_role":"Support","match_id":7057305063,"start_time":1678632306,"kills":0.9,"deaths":0,"creep_score":0.198,"gold_per_min":0.626,"tower_kills":0,"roshan_kills":0,"team_fight":2.1951,"obs_wards_planted":4.5,"camps_stacked":0.5,"runes_grabbed":0.5,"first_blood":0,"stuns":5.545,"total":14.9641},{"player_name":"AfterLife","team_name":"One Move","player_role":"Core","match_id":7057305063,"start_time":1678632306,"kills":1.2,"deaths":1.2,"creep_score":0.84,"gold_per_min":0.884,"tower_kills":1,"roshan_kills":1,"team_fight":2.1951,"obs_wards_planted":0,"camps_stacked":1.5,"runes_grabbed":0.5,"first_blood":0,"stuns":1.8833,"total":12.2024},{"player_name":"Kami","team_name":"HYDRA","player_role":"Core","match_id":7057305063,"start_time":1678632306,"kills":6.9,"deaths":1.8,"creep_score":2.013,"gold_per_min":1.824,"tower_kills":6,"roshan_kills":0,"team_fight":2.3864,"obs_wards_planted":0,"camps_stacked":1.5,"runes_grabbed":2.25,"first_blood":0,"stuns":3.2102,"total":27.8836},{"player_name":"HappyDyurara","team_name":"HYDRA","player_role":"Support","match_id":7057305063,"start_time":1678632306,"kills":0.3,"deaths":-1.5,"creep_score":0.183,"gold_per_min":0.644,"tower_kills":0,"roshan_kills":0,"team_fight":2.0454,"obs_wards_planted":11,"camps_stacked":0.5,"runes_grabbed":1.75,"first_blood":0,"stuns":4.6763,"total":19.5988},{"player_name":"Cloud","team_name":"HYDRA","player_role":"Core","match_id":7057305063,"start_time":1678632306,"kills":1.5,"deaths":0.9,"creep_score":1.104,"gold_per_min":1.398,"tower_kills":2,"roshan_kills":0,"team_fight":1.2273,"obs_wards_planted":0,"camps_stacked":1,"runes_grabbed":1.75,"first_blood":0,"stuns":6.8667,"total":17.746},{"player_name":"Worick","team_name":"HYDRA","player_role":"Mid","match_id":7057305063,"start_time":1678632306,"kills":3,"deaths":0.9,"creep_score":1.011,"gold_per_min":1.122,"tower_kills":0,"roshan_kills":1,"team_fight":2.3182,"obs_wards_planted":1,"camps_stacked":1.5,"runes_grabbed":5.75,"first_blood":4,"stuns":4.3082,"total":25.9094},{"player_name":"Lefitan","team_name":"HYDRA","player_role":"Core","match_id":7057305063,"start_time":1678632306,"kills":1.5,"deaths":0.6,"creep_score":0.252,"gold_per_min":0.682,"tower_kills":0,"roshan_kills":0,"team_fight":2.3182,"obs_wards_planted":1.5,"camps_stacked":3,"runes_grabbed":0,"first_blood":0,"stuns":0,"total":9.8522},{"player_name":"Worick","team_name":"HYDRA","player_role":"Mid","match_id":7057493428,"start_time":1678638075,"kills":1.5,"deaths":2.4,"creep_score":1.128,"gold_per_min":1.282,"tower_kills":1,"roshan_kills":1,"team_fight":1.8462,"obs_wards_planted":1,"camps_stacked":0,"runes_grabbed":4,"first_blood":0,"stuns":0.4933,"total":15.6495},{"player_name":"HappyDyurara","team_name":"HYDRA","player_role":"Support","match_id":7057493428,"start_time":1678638075,"kills":1.2,"deaths":1.2,"creep_score":0.198,"gold_per_min":0.67,"tower_kills":0,"roshan_kills":0,"team_fight":1.8462,"obs_wards_planted":5.5,"camps_stacked":0,"runes_grabbed":1,"first_blood":0,"stuns":2.36,"total":13.9741},{"player_name":"Lefitan","team_name":"HYDRA","player_role":"Core","match_id":7057493428,"start_time":1678638075,"kills":0.9,"deaths":1.5,"creep_score":0.318,"gold_per_min":0.7,"tower_kills":1,"roshan_kills":0,"team_fight":1.8462,"obs_wards_planted":3,"camps_stacked":2.5,"runes_grabbed":0.5,"first_blood":0,"stuns":0.785,"total":13.0491},{"player_name":"Cloud","team_name":"HYDRA","player_role":"Core","match_id":7057493428,"start_time":1678638075,"kills":0.3,"deaths":2.1,"creep_score":1.008,"gold_per_min":1.068,"tower_kills":2,"roshan_kills":0,"team_fight":1.3846,"obs_wards_planted":0,"camps_stacked":0.5,"runes_grabbed":0.75,"first_blood":0,"stuns":1.305,"total":10.4156},{"player_name":"Kami","team_name":"HYDRA","player_role":"Core","match_id":7057493428,"start_time":1678638075,"kills":3.9,"deaths":2.4,"creep_score":1.386,"gold_per_min":1.506,"tower_kills":4,"roshan_kills":1,"team_fight":2.1923,"obs_wards_planted":0,"camps_stacked":1,"runes_grabbed":0.25,"first_blood":0,"stuns":0,"total":17.6343},{"player_name":"Munkushi~太阳","team_name":"One Move","player_role":"Core","match_id":7057493428,"start_time":1678638075,"kills":2.4,"deaths":2.1,"creep_score":0.996,"gold_per_min":1.15,"tower_kills":1,"roshan_kills":0,"team_fight":2,"obs_wards_planted":0,"camps_stacked":1,"runes_grabbed":0.25,"first_blood":0,"stuns":0.5617,"total":11.4577},{"player_name":"Ainkrad","team_name":"One Move","player_role":"Mid","match_id":7057493428,"start_time":1678638075,"kills":1.5,"deaths":1.2,"creep_score":0.693,"gold_per_min":0.876,"tower_kills":0,"roshan_kills":0,"team_fight":2.3333,"obs_wards_planted":1,"camps_stacked":0,"runes_grabbed":2.75,"first_blood":0,"stuns":0.93,"total":11.2824},{"player_name":"pantomem","team_name":"One Move","player_role":"Support","match_id":7057493428,"start_time":1678638075,"kills":0.3,"deaths":1.2,"creep_score":0.306,"gold_per_min":0.572,"tower_kills":2,"roshan_kills":0,"team_fight":1.6667,"obs_wards_planted":5.5,"camps_stacked":0,"runes_grabbed":1,"first_blood":0,"stuns":0.295,"total":12.8397},{"player_name":"Gilgir","team_name":"One Move","player_role":"Support","match_id":7057493428,"start_time":1678638075,"kills":0.3,"deaths":1.2,"creep_score":0.222,"gold_per_min":0.468,"tower_kills":0,"roshan_kills":0,"team_fight":0.8333,"obs_wards_planted":2.5,"camps_stacked":0,"runes_grabbed":1.25,"first_blood":0,"stuns":1.2716,"total":8.045},{"player_name":"AfterLife","team_name":"One Move","player_role":"Core","match_id":7057493428,"start_time":1678638075,"kills":0.6,"deaths":1.5,"creep_score":0.648,"gold_per_min":0.83,"tower_kills":1,"roshan_kills":0,"team_fight":2.3333,"obs_wards_planted":0,"camps_stacked":0,"runes_grabbed":0.5,"first_blood":0,"stuns":0.2983,"total":7.7097},{"player_name":"Munkushi~太阳","team_name":"One Move","player_role":"Core","match_id":7057598159,"start_time":1678642150,"kills":3.6,"deaths":3,"creep_score":1.239,"gold_per_min":1.442,"tower_kills":1,"roshan_kills":1,"team_fight":2.1628,"obs_wards_planted":0,"camps_stacked":0.5,"runes_grabbed":0.75,"first_blood":0,"stuns":0.2033,"total":14.8971},{"player_name":"Ainkrad","team_name":"One Move","player_role":"Mid","match_id":7057598159,"start_time":1678642150,"kills":4.2,"deaths":2.7,"creep_score":0.876,"gold_per_min":1.19,"tower_kills":1,"roshan_kills":0,"team_fight":2.5116,"obs_wards_planted":1,"camps_stacked":0.5,"runes_grabbed":4.25,"first_blood":0,"stuns":3.0716,"total":21.2992},{"player_name":"pantomem","team_name":"One Move","player_role":"Support","match_id":7057598159,"start_time":1678642150,"kills":0.9,"deaths":1.5,"creep_score":0.405,"gold_per_min":0.704,"tower_kills":1,"roshan_kills":1,"team_fight":1.1861,"obs_wards_planted":4.5,"camps_stacked":1.5,"runes_grabbed":1.5,"first_blood":4,"stuns":0.4,"total":18.5951},{"player_name":"Gilgir","team_name":"One Move","player_role":"Support","match_id":7057598159,"start_time":1678642150,"kills":1.2,"deaths":1.2,"creep_score":0.195,"gold_per_min":0.678,"tower_kills":0,"roshan_kills":0,"team_fight":1.6744,"obs_wards_planted":4,"camps_stacked":0.5,"runes_grabbed":1.5,"first_blood":0,"stuns":3.4065,"total":14.3539},{"player_name":"AfterLife","team_name":"One Move","player_role":"Core","match_id":7057598159,"start_time":1678642150,"kills":3,"deaths":2.1,"creep_score":0.945,"gold_per_min":1.168,"tower_kills":0,"roshan_kills":0,"team_fight":1.3256,"obs_wards_planted":0,"camps_stacked":1,"runes_grabbed":0.75,"first_blood":0,"stuns":0,"total":10.2886},{"player_name":"Worick","team_name":"HYDRA","player_role":"Mid","match_id":7057598159,"start_time":1678642150,"kills":1.8,"deaths":0,"creep_score":0.771,"gold_per_min":0.842,"tower_kills":0,"roshan_kills":0,"team_fight":2,"obs_wards_planted":1.5,"camps_stacked":2,"runes_grabbed":2.75,"first_blood":0,"stuns":1.94,"total":13.603},{"player_name":"HappyDyurara","team_name":"HYDRA","player_role":"Support","match_id":7057598159,"start_time":1678642150,"kills":0.3,"deaths":0.3,"creep_score":0.039,"gold_per_min":0.352,"tower_kills":0,"roshan_kills":0,"team_fight":1.6,"obs_wards_planted":7,"camps_stacked":0,"runes_grabbed":0.75,"first_blood":0,"stuns":1.1917,"total":11.5327},{"player_name":"Cloud","team_name":"HYDRA","player_role":"Core","match_id":7057598159,"start_time":1678642150,"kills":0.9,"deaths":1.8,"creep_score":0.807,"gold_per_min":0.896,"tower_kills":0,"roshan_kills":0,"team_fight":2.2,"obs_wards_planted":0,"camps_stacked":0.5,"runes_grabbed":0,"first_blood":0,"stuns":1.6717,"total":8.7746},{"player_name":"Lefitan","team_name":"HYDRA","player_role":"Core","match_id":7057598159,"start_time":1678642150,"kills":0.9,"deaths":-1.5,"creep_score":0.273,"gold_per_min":0.476,"tower_kills":0,"roshan_kills":0,"team_fight":2.2,"obs_wards_planted":1.5,"camps_stacked":0,"runes_grabbed":0.75,"first_blood":0,"stuns":2.8345,"total":7.4335},{"player_name":"Kami","team_name":"HYDRA","player_role":"Core","match_id":7057598159,"start_time":1678642150,"kills":0.6,"deaths":1.5,"creep_score":1.212,"gold_per_min":1.148,"tower_kills":2,"roshan_kills":0,"team_fight":2,"obs_wards_planted":0,"camps_stacked":0.5,"runes_grabbed":0.5,"first_blood":0,"stuns":0.0017,"total":9.4617},{"player_name":"Munkushi~太阳","team_name":"One Move","player_role":"Core","match_id":7059915471,"start_time":1678791642,"kills":0,"deaths":1.8,"creep_score":0.375,"gold_per_min":0.734,"tower_kills":0,"roshan_kills":0,"team_fight":0.8571,"obs_wards_planted":0,"camps_stacked":0,"runes_grabbed":0.25,"first_blood":0,"stuns":0,"total":4.0161},{"player_name":"Ainkrad","team_name":"One Move","player_role":"Mid","match_id":7059915471,"start_time":1678791642,"kills":1.5,"deaths":2.1,"creep_score":0.48,"gold_per_min":0.966,"tower_kills":1,"roshan_kills":0,"team_fight":3,"obs_wards_planted":1,"camps_stacked":0.5,"runes_grabbed":1.5,"first_blood":0,"stuns":0.5,"total":12.546},{"player_name":"pantomem","team_name":"One Move","player_role":"Support","match_id":7059915471,"start_time":1678791642,"kills":0.3,"deaths":1.2,"creep_score":0.072,"gold_per_min":0.386,"tower_kills":0,"roshan_kills":0,"team_fight":3,"obs_wards_planted":2,"camps_stacked":0.5,"runes_grabbed":0,"first_blood":0,"stuns":0,"total":7.458},{"player_name":"Gilgir","team_name":"One Move","player_role":"Support","match_id":7059915471,"start_time":1678791642,"kills":0,"deaths":1.2,"creep_score":0.057,"gold_per_min":0.312,"tower_kills":0,"roshan_kills":0,"team_fight":1.7143,"obs_wards_planted":2,"camps_stacked":0,"runes_grabbed":1.25,"first_blood":0,"stuns":1.7282,"total":8.2615},{"player_name":"AfterLife","team_name":"One Move","player_role":"Core","match_id":7059915471,"start_time":1678791642,"kills":0.3,"deaths":2.7,"creep_score":0.444,"gold_per_min":0.828,"tower_kills":0,"roshan_kills":0,"team_fight":1.2857,"obs_wards_planted":0,"camps_stacked":0,"runes_grabbed":0,"first_blood":0,"stuns":0.07,"total":5.6277},{"player_name":"Yatoro雨","team_name":"Team Spirit","player_role":"Core","match_id":7059915471,"start_time":1678791642,"kills":0.6,"deaths":3,"creep_score":0.69,"gold_per_min":1.118,"tower_kills":0,"roshan_kills":0,"team_fight":0.45,"obs_wards_planted":0,"camps_stacked":2,"runes_grabbed":0.25,"first_blood":0,"stuns":0.13,"total":8.238},{"player_name":"Miposhka","team_name":"Team Spirit","player_role":"Support","match_id":7059915471,"start_time":1678791642,"kills":0.3,"deaths":2.4,"creep_score":0.129,"gold_per_min":0.584,"tower_kills":0,"roshan_kills":0,"team_fight":2.55,"obs_wards_planted":2,"camps_stacked":1,"runes_grabbed":0.25,"first_blood":0,"stuns":0,"total":9.213},{"player_name":"Mira","team_name":"Team Spirit","player_role":"Support","match_id":7059915471,"start_time":1678791642,"kills":1.5,"deaths":2.1,"creep_score":0.117,"gold_per_min":0.69,"tower_kills":1,"roshan_kills":0,"team_fight":3,"obs_wards_planted":2,"camps_stacked":1,"runes_grabbed":0.5,"first_blood":0,"stuns":0.6167,"total":12.5237},{"player_name":"Larl","team_name":"Team Spirit","player_role":"Mid","match_id":7059915471,"start_time":1678791642,"kills":1.8,"deaths":2.4,"creep_score":0.468,"gold_per_min":1.048,"tower_kills":0,"roshan_kills":1,"team_fight":1.95,"obs_wards_planted":1,"camps_stacked":0.5,"runes_grabbed":2.5,"first_blood":0,"stuns":0.675,"total":13.341},{"player_name":"Collapse","team_name":"Team Spirit","player_role":"Core","match_id":7059915471,"start_time":1678791642,"kills":1.8,"deaths":3,"creep_score":0.591,"gold_per_min":1.318,"tower_kills":5,"roshan_kills":0,"team_fight":1.8,"obs_wards_planted":0,"camps_stacked":2.5,"runes_grabbed":0.5,"first_blood":4,"stuns":0.655,"total":21.164},{"player_name":"Munkushi~太阳","team_name":"One Move","player_role":"Core","match_id":7059972690,"start_time":1678794624,"kills":3,"deaths":2.4,"creep_score":1.293,"gold_per_min":1.298,"tower_kills":3,"roshan_kills":1,"team_fight":1.875,"obs_wards_planted":0,"camps_stacked":2,"runes_grabbed":1,"first_blood":0,"stuns":0.6983,"total":17.5644},{"player_name":"Ainkrad","team_name":"One Move","player_role":"Mid","match_id":7059972690,"start_time":1678794624,"kills":2.1,"deaths":2.1,"creep_score":0.885,"gold_per_min":1.11,"tower_kills":0,"roshan_kills":1,"team_fight":2.1562,"obs_wards_planted":1,"camps_stacked":0,"runes_grabbed":2.75,"first_blood":0,"stuns":0.7733,"total":13.8746},{"player_name":"pantomem","team_name":"One Move","player_role":"Support","match_id":7059972690,"start_time":1678794624,"kills":1.2,"deaths":1.8,"creep_score":0.33,"gold_per_min":0.704,"tower_kills":1,"roshan_kills":0,"team_fight":1.875,"obs_wards_planted":5.5,"camps_stacked":0.5,"runes_grabbed":1.25,"first_blood":0,"stuns":0.7,"total":14.859},{"player_name":"Gilgir","team_name":"One Move","player_role":"Support","match_id":7059972690,"start_time":1678794624,"kills":1.5,"deaths":1.8,"creep_score":0.285,"gold_per_min":0.722,"tower_kills":1,"roshan_kills":0,"team_fight":2.1562,"obs_wards_planted":4,"camps_stacked":1,"runes_grabbed":1.25,"first_blood":0,"stuns":4.0064,"total":17.7196},{"player_name":"AfterLife","team_name":"One Move","player_role":"Core","match_id":7059972690,"start_time":1678794624,"kills":1.8,"deaths":1.2,"creep_score":0.726,"gold_per_min":0.958,"tower_kills":1,"roshan_kills":0,"team_fight":2.0625,"obs_wards_planted":0,"camps_stacked":1,"runes_grabbed":0.75,"first_blood":0,"stuns":0,"total":9.4965},{"player_name":"Yatoro雨","team_name":"Team Spirit","player_role":"Core","match_id":7059972690,"start_time":1678794624,"kills":2.1,"deaths":2.1,"creep_score":1.53,"gold_per_min":1.822,"tower_kills":2,"roshan_kills":0,"team_fight":1.8947,"obs_wards_planted":0,"camps_stacked":0.5,"runes_grabbed":2,"first_blood":4,"stuns":3.7244,"total":21.6711},{"player_name":"Miposhka","team_name":"Team Spirit","player_role":"Support","match_id":7059972690,"start_time":1678794624,"kills":0.3,"deaths":0,"creep_score":0.081,"gold_per_min":0.426,"tower_kills":0,"roshan_kills":0,"team_fight":2.0526,"obs_wards_planted":8,"camps_stacked":2.5,"runes_grabbed":1.25,"first_blood":0,"stuns":3.36,"total":17.9696},{"player_name":"Mira","team_name":"Team Spirit","player_role":"Support","match_id":7059972690,"start_time":1678794624,"kills":1.5,"deaths":0,"creep_score":0.165,"gold_per_min":0.516,"tower_kills":0,"roshan_kills":0,"team_fight":2.0526,"obs_wards_planted":1,"camps_stacked":2.5,"runes_grabbed":0.25,"first_blood":0,"stuns":2.4466,"total":10.4303},{"player_name":"Larl","team_name":"Team Spirit","player_role":"Mid","match_id":7059972690,"start_time":1678794624,"kills":1.2,"deaths":2.1,"creep_score":0.753,"gold_per_min":0.884,"tower_kills":1,"roshan_kills":1,"team_fight":2.0526,"obs_wards_planted":1,"camps_stacked":0,"runes_grabbed":1.75,"first_blood":0,"stuns":0.4483,"total":12.1879},{"player_name":"Collapse","team_name":"Team Spirit","player_role":"Core","match_id":7059972690,"start_time":1678794624,"kills":0.6,"deaths":1.2,"creep_score":0.828,"gold_per_min":0.878,"tower_kills":0,"roshan_kills":0,"team_fight":1.8947,"obs_wards_planted":0,"camps_stacked":0,"runes_grabbed":0.25,"first_blood":0,"stuns":4.2125,"total":9.8632},{"player_name":"Munkushi~太阳","team_name":"One Move","player_role":"Core","match_id":7060096979,"start_time":1678799465,"kills":1.8,"deaths":1.8,"creep_score":0.666,"gold_per_min":0.866,"tower_kills":0,"roshan_kills":0,"team_fight":1.0909,"obs_wards_planted":0,"camps_stacked":1,"runes_grabbed":0,"first_blood":0,"stuns":1.2284,"total":8.4513},{"player_name":"Ainkrad","team_name":"One Move","player_role":"Mid","match_id":7060096979,"start_time":1678799465,"kills":1.8,"deaths":1.5,"creep_score":0.618,"gold_per_min":0.846,"tower_kills":1,"roshan_kills":0,"team_fight":2.1818,"obs_wards_planted":1,"camps_stacked":0,"runes_grabbed":1.5,"first_blood":0,"stuns":2.1683,"total":12.6141},{"player_name":"pantomem","team_name":"One Move","player_role":"Support","match_id":7060096979,"start_time":1678799465,"kills":0.9,"deaths":-0.3,"creep_score":0.171,"gold_per_min":0.468,"tower_kills":0,"roshan_kills":0,"team_fight":1.2273,"obs_wards_planted":5.5,"camps_stacked":0,"runes_grabbed":1.5,"first_blood":0,"stuns":0.7767,"total":10.2429},{"player_name":"Gilgir","team_name":"One Move","player_role":"Support","match_id":7060096979,"start_time":1678799465,"kills":1.2,"deaths":0,"creep_score":0.102,"gold_per_min":0.45,"tower_kills":0,"roshan_kills":0,"team_fight":1.9091,"obs_wards_planted":2.5,"camps_stacked":1.5,"runes_grabbed":0.75,"first_blood":0,"stuns":2.9648,"total":11.3759},{"player_name":"AfterLife","team_name":"One Move","player_role":"Core","match_id":7060096979,"start_time":1678799465,"kills":0.9,"deaths":2.4,"creep_score":0.609,"gold_per_min":0.77,"tower_kills":1,"roshan_kills":0,"team_fight":2.3182,"obs_wards_planted":0,"camps_stacked":1,"runes_grabbed":0.25,"first_blood":0,"stuns":0.3966,"total":9.6438},{"player_name":"Yatoro雨","team_name":"Team Spirit","player_role":"Core","match_id":7060096979,"start_time":1678799465,"kills":3.9,"deaths":2.7,"creep_score":1.104,"gold_per_min":1.52,"tower_kills":4,"roshan_kills":2,"team_fight":2.25,"obs_wards_planted":0.5,"camps_stacked":0.5,"runes_grabbed":1.5,"first_blood":4,"stuns":1.8249,"total":25.7989},{"player_name":"Miposhka","team_name":"Team Spirit","player_role":"Support","match_id":7060096979,"start_time":1678799465,"kills":0.3,"deaths":0.6,"creep_score":0.162,"gold_per_min":0.568,"tower_kills":0,"roshan_kills":0,"team_fight":1.5938,"obs_wards_planted":4,"camps_stacked":1.5,"runes_grabbed":0.5,"first_blood":0,"stuns":1.615,"total":10.8387},{"player_name":"Mira","team_name":"Team Spirit","player_role":"Support","match_id":7060096979,"start_time":1678799465,"kills":0.9,"deaths":0.3,"creep_score":0.222,"gold_per_min":0.614,"tower_kills":1,"roshan_kills":0,"team_fight":1.6875,"obs_wards_planted":3,"camps_stacked":1,"runes_grabbed":1.25,"first_blood":0,"stuns":0.74,"total":10.7135},{"player_name":"Larl","team_name":"Team Spirit","player_role":"Mid","match_id":7060096979,"start_time":1678799465,"kills":3.9,"deaths":2.4,"creep_score":0.669,"gold_per_min":1.082,"tower_kills":0,"roshan_kills":0,"team_fight":1.9688,"obs_wards_planted":0.5,"camps_stacked":0.5,"runes_grabbed":1.5,"first_blood":0,"stuns":0.625,"total":13.1447},{"player_name":"Collapse","team_name":"Team Spirit","player_role":"Core","match_id":7060096979,"start_time":1678799465,"kills":0.6,"deaths":2.4,"creep_score":0.858,"gold_per_min":1.064,"tower_kills":2,"roshan_kills":0,"team_fight":2.3438,"obs_wards_planted":0,"camps_stacked":0.5,"runes_grabbed":1,"first_blood":0,"stuns":3.7508,"total":14.5166},{"player_name":"Solo","team_name":"HellRaisers","player_role":"Support","match_id":7060209585,"start_time":1678803798,"kills":0,"deaths":1.5,"creep_score":0.276,"gold_per_min":0.69,"tower_kills":2,"roshan_kills":1,"team_fight":1.5652,"obs_wards_planted":2,"camps_stacked":0,"runes_grabbed":0.5,"first_blood":0,"stuns":0,"total":9.5312},{"player_name":"kiyotaka","team_name":"HellRaisers","player_role":"Mid","match_id":7060209585,"start_time":1678803798,"kills":3,"deaths":2.4,"creep_score":0.804,"gold_per_min":1.248,"tower_kills":0,"roshan_kills":1,"team_fight":1.9565,"obs_wards_planted":0.5,"camps_stacked":0,"runes_grabbed":4,"first_blood":0,"stuns":1.39,"total":16.2985},{"player_name":"MieRo`","team_name":"HellRaisers","player_role":"Core","match_id":7060209585,"start_time":1678803798,"kills":2.4,"deaths":3,"creep_score":0.498,"gold_per_min":1.068,"tower_kills":3,"roshan_kills":0,"team_fight":2.087,"obs_wards_planted":0,"camps_stacked":0.5,"runes_grabbed":0.5,"first_blood":0,"stuns":2.6556,"total":15.7086},{"player_name":"Antares","team_name":"HellRaisers","player_role":"Support","match_id":7060209585,"start_time":1678803798,"kills":0.3,"deaths":2.4,"creep_score":0.21,"gold_per_min":0.664,"tower_kills":0,"roshan_kills":0,"team_fight":1.4348,"obs_wards_planted":4,"camps_stacked":1.5,"runes_grabbed":1,"first_blood":0,"stuns":1.09,"total":12.5988},{"player_name":"RAMZES666","team_name":"HellRaisers","player_role":"Core","match_id":7060209585,"start_time":1678803798,"kills":1.2,"deaths":2.4,"creep_score":0.909,"gold_per_min":1.304,"tower_kills":4,"roshan_kills":0,"team_fight":1.1739,"obs_wards_planted":0.5,"camps_stacked":0,"runes_grabbed":0,"first_blood":0,"stuns":0.1327,"total":11.6196},{"player_name":"Kiritych~","team_name":"Virtus.pro","player_role":"Core","match_id":7060209585,"start_time":1678803798,"kills":1.8,"deaths":1.5,"creep_score":0.897,"gold_per_min":1.194,"tower_kills":2,"roshan_kills":0,"team_fight":1.9091,"obs_wards_planted":0,"camps_stacked":0.5,"runes_grabbed":0.25,"first_blood":0,"stuns":0.2367,"total":10.2868},{"player_name":"sayuw","team_name":"Virtus.pro","player_role":"Support","match_id":7060209585,"start_time":1678803798,"kills":0,"deaths":1.8,"creep_score":0.078,"gold_per_min":0.386,"tower_kills":0,"roshan_kills":0,"team_fight":2.4545,"obs_wards_planted":3.5,"camps_stacked":0,"runes_grabbed":1.25,"first_blood":0,"stuns":1.7217,"total":11.1902},{"player_name":"Fng","team_name":"Virtus.pro","player_role":"Support","match_id":7060209585,"start_time":1678803798,"kills":0.3,"deaths":0.3,"creep_score":0.03,"gold_per_min":0.426,"tower_kills":0,"roshan_kills":0,"team_fight":1.3636,"obs_wards_planted":2,"camps_stacked":0.5,"runes_grabbed":0.25,"first_blood":0,"stuns":0,"total":5.1696},{"player_name":"squad1x","team_name":"Virtus.pro","player_role":"Mid","match_id":7060209585,"start_time":1678803798,"kills":1.2,"deaths":2.1,"creep_score":0.795,"gold_per_min":1.062,"tower_kills":0,"roshan_kills":0,"team_fight":2.7273,"obs_wards_planted":1.5,"camps_stacked":0,"runes_grabbed":1.5,"first_blood":4,"stuns":0.42,"total":15.3043},{"player_name":"Noticed","team_name":"Virtus.pro","player_role":"Core","match_id":7060209585,"start_time":1678803798,"kills":0,"deaths":2.4,"creep_score":0.798,"gold_per_min":1.016,"tower_kills":2,"roshan_kills":0,"team_fight":1.0909,"obs_wards_planted":0,"camps_stacked":2.5,"runes_grabbed":0.75,"first_blood":0,"stuns":0.2983,"total":10.8532}],"result_average":[{"player_name":"mellojul","team_name":"Natus Vincere","player_role":"Mid","kills":0.8,"deaths":2.2,"creep_score":1.308,"gold_per_min":1.2973,"tower_kills":1.6667,"roshan_kills":0,"team_fight":1.9272,"obs_wards_planted":0.6667,"camps_stacked":0.8333,"runes_grabbed":2.5833,"first_blood":0,"stuns":1.7886,"total":15.0711},{"player_name":"Worick","team_name":"HYDRA","player_role":"Mid","kills":2.1,"deaths":1.1,"creep_score":0.97,"gold_per_min":1.082,"tower_kills":0.3333,"roshan_kills":0.6667,"team_fight":2.0548,"obs_wards_planted":1.1667,"camps_stacked":1.1667,"runes_grabbed":4.1667,"first_blood":1.3333,"stuns":2.2472,"total":18.3873},{"player_name":"AfterLife","team_name":"One Move","player_role":"Core","kills":1.3,"deaths":1.85,"creep_score":0.702,"gold_per_min":0.9063,"tower_kills":0.6667,"roshan_kills":0.1667,"team_fight":1.9201,"obs_wards_planted":0,"camps_stacked":0.75,"runes_grabbed":0.4583,"first_blood":0,"stuns":0.4414,"total":9.1614},{"player_name":"Malady","team_name":"Natus Vincere","player_role":"Support","kills":0.3,"deaths":1.5,"creep_score":0.085,"gold_per_min":0.478,"tower_kills":0,"roshan_kills":0,"team_fight":1.7756,"obs_wards_planted":4.3333,"camps_stacked":1.5,"runes_grabbed":1.25,"first_blood":0,"stuns":0,"total":11.222},{"player_name":"Fng","team_name":"Virtus.pro","player_role":"Support","kills":0.3,"deaths":0.3,"creep_score":0.03,"gold_per_min":0.426,"tower_kills":0,"roshan_kills":0,"team_fight":1.3636,"obs_wards_planted":2,"camps_stacked":0.5,"runes_grabbed":0.25,"first_blood":0,"stuns":0,"total":5.1696},{"player_name":"Larl","team_name":"Team Spirit","player_role":"Mid","kills":2.3,"deaths":2.3,"creep_score":0.63,"gold_per_min":1.0047,"tower_kills":0.3333,"roshan_kills":0.6667,"team_fight":1.9905,"obs_wards_planted":0.8333,"camps_stacked":0.3333,"runes_grabbed":1.9167,"first_blood":0,"stuns":0.5828,"total":12.8912},{"player_name":"pantomem","team_name":"One Move","player_role":"Support","kills":0.75,"deaths":0.75,"creep_score":0.2315,"gold_per_min":0.5723,"tower_kills":0.6667,"roshan_kills":0.1667,"team_fight":1.773,"obs_wards_planted":5.0833,"camps_stacked":0.4167,"runes_grabbed":1.0833,"first_blood":0.6667,"stuns":0.5714,"total":12.7315},{"player_name":"Miposhka","team_name":"Team Spirit","player_role":"Support","kills":0.3,"deaths":1,"creep_score":0.124,"gold_per_min":0.526,"tower_kills":0,"roshan_kills":0,"team_fight":2.0655,"obs_wards_planted":4.6667,"camps_stacked":1.6667,"runes_grabbed":0.6667,"first_blood":0,"stuns":1.6583,"total":12.6738},{"player_name":"SoNNeikO","team_name":"Darkside","player_role":"Support","kills":0.6,"deaths":0.7,"creep_score":0.172,"gold_per_min":0.53,"tower_kills":0,"roshan_kills":0,"team_fight":2.2978,"obs_wards_planted":5.1667,"camps_stacked":3,"runes_grabbed":2,"first_blood":0,"stuns":1.3161,"total":15.7826},{"player_name":"squad1x","team_name":"Virtus.pro","player_role":"Mid","kills":1.2,"deaths":2.1,"creep_score":0.795,"gold_per_min":1.062,"tower_kills":0,"roshan_kills":0,"team_fight":2.7273,"obs_wards_planted":1.5,"camps_stacked":0,"runes_grabbed":1.5,"first_blood":4,"stuns":0.42,"total":15.3043},{"player_name":"RAMZES666","team_name":"HellRaisers","player_role":"Core","kills":1.2,"deaths":2.4,"creep_score":0.909,"gold_per_min":1.304,"tower_kills":4,"roshan_kills":0,"team_fight":1.1739,"obs_wards_planted":0.5,"camps_stacked":0,"runes_grabbed":0,"first_blood":0,"stuns":0.1327,"total":11.6196},{"player_name":"Solo","team_name":"HellRaisers","player_role":"Support","kills":0,"deaths":1.5,"creep_score":0.276,"gold_per_min":0.69,"tower_kills":2,"roshan_kills":1,"team_fight":1.5652,"obs_wards_planted":2,"camps_stacked":0,"runes_grabbed":0.5,"first_blood":0,"stuns":0,"total":9.5312},{"player_name":"Lefitan","team_name":"HYDRA","player_role":"Core","kills":1.1,"deaths":0.2,"creep_score":0.281,"gold_per_min":0.6193,"tower_kills":0.3333,"roshan_kills":0,"team_fight":2.1214,"obs_wards_planted":2,"camps_stacked":1.8333,"runes_grabbed":0.4167,"first_blood":0,"stuns":1.2065,"total":10.1116},{"player_name":"sayuw","team_name":"Virtus.pro","player_role":"Support","kills":0,"deaths":1.8,"creep_score":0.078,"gold_per_min":0.386,"tower_kills":0,"roshan_kills":0,"team_fight":2.4545,"obs_wards_planted":3.5,"camps_stacked":0,"runes_grabbed":1.25,"first_blood":0,"stuns":1.7217,"total":11.1902},{"player_name":"dizzying","team_name":"Darkside","player_role":"Core","kills":1.9,"deaths":1.3,"creep_score":1.139,"gold_per_min":1.142,"tower_kills":1.3333,"roshan_kills":1,"team_fight":2.0092,"obs_wards_planted":0.1667,"camps_stacked":0.6667,"runes_grabbed":0.9167,"first_blood":1.3333,"stuns":0.7317,"total":13.6386},{"player_name":"RodjER","team_name":"Darkside","player_role":"Support","kills":0.4,"deaths":1.6,"creep_score":0.211,"gold_per_min":0.522,"tower_kills":0,"roshan_kills":0,"team_fight":2.0947,"obs_wards_planted":4.1667,"camps_stacked":1.1667,"runes_grabbed":0.5833,"first_blood":0,"stuns":3.6639,"total":14.4083},{"player_name":"Antares","team_name":"HellRaisers","player_role":"Support","kills":0.3,"deaths":2.4,"creep_score":0.21,"gold_per_min":0.664,"tower_kills":0,"roshan_kills":0,"team_fight":1.4348,"obs_wards_planted":4,"camps_stacked":1.5,"runes_grabbed":1,"first_blood":0,"stuns":1.09,"total":12.5988},{"player_name":"MieRo`","team_name":"HellRaisers","player_role":"Core","kills":2.4,"deaths":3,"creep_score":0.498,"gold_per_min":1.068,"tower_kills":3,"roshan_kills":0,"team_fight":2.087,"obs_wards_planted":0,"camps_stacked":0.5,"runes_grabbed":0.5,"first_blood":0,"stuns":2.6556,"total":15.7086},{"player_name":"Cloud","team_name":"HYDRA","player_role":"Core","kills":0.9,"deaths":1.6,"creep_score":0.973,"gold_per_min":1.1207,"tower_kills":1.3333,"roshan_kills":0,"team_fight":1.604,"obs_wards_planted":0,"camps_stacked":0.6667,"runes_grabbed":0.8333,"first_blood":0,"stuns":3.2811,"total":12.3121},{"player_name":"Kiritych~","team_name":"Virtus.pro","player_role":"Core","kills":1.8,"deaths":1.5,"creep_score":0.897,"gold_per_min":1.194,"tower_kills":2,"roshan_kills":0,"team_fight":1.9091,"obs_wards_planted":0,"camps_stacked":0.5,"runes_grabbed":0.25,"first_blood":0,"stuns":0.2367,"total":10.2868},{"player_name":"Gilgir","team_name":"One Move","player_role":"Support","kills":0.85,"deaths":0.9,"creep_score":0.1765,"gold_per_min":0.5427,"tower_kills":0.1667,"roshan_kills":0,"team_fight":1.7471,"obs_wards_planted":3.25,"camps_stacked":0.5833,"runes_grabbed":1.0833,"first_blood":0,"stuns":3.1538,"total":12.4533},{"player_name":"shigetsu","team_name":"Natus Vincere","player_role":"Core","kills":3.2,"deaths":2.2,"creep_score":1.721,"gold_per_min":1.598,"tower_kills":2,"roshan_kills":1.3333,"team_fight":1.9989,"obs_wards_planted":0.3333,"camps_stacked":0.3333,"runes_grabbed":1.1667,"first_blood":0,"stuns":1.1945,"total":17.0791},{"player_name":"Noticed","team_name":"Virtus.pro","player_role":"Core","kills":0,"deaths":2.4,"creep_score":0.798,"gold_per_min":1.016,"tower_kills":2,"roshan_kills":0,"team_fight":1.0909,"obs_wards_planted":0,"camps_stacked":2.5,"runes_grabbed":0.75,"first_blood":0,"stuns":0.2983,"total":10.8532},{"player_name":"Ainkrad","team_name":"One Move","player_role":"Mid","kills":2.65,"deaths":1.55,"creep_score":0.783,"gold_per_min":1.0367,"tower_kills":0.6667,"roshan_kills":0.3333,"team_fight":2.4573,"obs_wards_planted":1,"camps_stacked":0.1667,"runes_grabbed":2.625,"first_blood":0,"stuns":2.0247,"total":15.2934},{"player_name":"Malik","team_name":"Natus Vincere","player_role":"Core","kills":1.4,"deaths":1.7,"creep_score":1.148,"gold_per_min":1.192,"tower_kills":2.3333,"roshan_kills":0,"team_fight":1.9154,"obs_wards_planted":0.3333,"camps_stacked":1.8333,"runes_grabbed":1.25,"first_blood":2.6667,"stuns":1.8533,"total":17.6254},{"player_name":"Blizzy","team_name":"Darkside","player_role":"Core","kills":0.5,"deaths":1.3,"creep_score":0.951,"gold_per_min":0.9493,"tower_kills":1.3333,"roshan_kills":0.3333,"team_fight":2.0899,"obs_wards_planted":0,"camps_stacked":2,"runes_grabbed":0.5833,"first_blood":0,"stuns":2.4967,"total":12.5369},{"player_name":"Kami","team_name":"HYDRA","player_role":"Core","kills":3.8,"deaths":1.9,"creep_score":1.537,"gold_per_min":1.4927,"tower_kills":4,"roshan_kills":0.3333,"team_fight":2.1929,"obs_wards_planted":0,"camps_stacked":1,"runes_grabbed":1,"first_blood":0,"stuns":1.0706,"total":18.3265},{"player_name":"Mira","team_name":"Team Spirit","player_role":"Support","kills":1.3,"deaths":0.8,"creep_score":0.168,"gold_per_min":0.6067,"tower_kills":0.6667,"roshan_kills":0,"team_fight":2.2467,"obs_wards_planted":2,"camps_stacked":1.5,"runes_grabbed":0.6667,"first_blood":0,"stuns":1.2678,"total":11.2225},{"player_name":"Collapse","team_name":"Team Spirit","player_role":"Core","kills":1,"deaths":2.2,"creep_score":0.759,"gold_per_min":1.0867,"tower_kills":2.3333,"roshan_kills":0,"team_fight":2.0128,"obs_wards_planted":0,"camps_stacked":1,"runes_grabbed":0.5833,"first_blood":1.3333,"stuns":2.8728,"total":15.1813},{"player_name":"Yatoro雨","team_name":"Team Spirit","player_role":"Core","kills":2.2,"deaths":2.6,"creep_score":1.108,"gold_per_min":1.4867,"tower_kills":2,"roshan_kills":0.6667,"team_fight":1.5316,"obs_wards_planted":0.1667,"camps_stacked":1,"runes_grabbed":1.25,"first_blood":2.6667,"stuns":1.8931,"total":18.5694},{"player_name":"Danial","team_name":"Natus Vincere","player_role":"Support","kills":2.7,"deaths":1.7,"creep_score":0.167,"gold_per_min":0.63,"tower_kills":0.3333,"roshan_kills":0,"team_fight":2.2378,"obs_wards_planted":5,"camps_stacked":0.6667,"runes_grabbed":0.75,"first_blood":0,"stuns":0.1704,"total":14.3552},{"player_name":"HappyDyurara","team_name":"HYDRA","player_role":"Support","kills":0.6,"deaths":-1.8477e-17,"creep_score":0.14,"gold_per_min":0.5553,"tower_kills":0,"roshan_kills":0,"team_fight":1.8305,"obs_wards_planted":7.8333,"camps_stacked":0.1667,"runes_grabbed":1.1667,"first_blood":0,"stuns":2.7427,"total":15.0352},{"player_name":"reibl","team_name":"Darkside","player_role":"Mid","kills":2.3,"deaths":1.5,"creep_score":1.294,"gold_per_min":1.2967,"tower_kills":2.6667,"roshan_kills":0.3333,"team_fight":2.1759,"obs_wards_planted":0.8333,"camps_stacked":0.8333,"runes_grabbed":2.75,"first_blood":0,"stuns":2.1833,"total":18.1666},{"player_name":"kiyotaka","team_name":"HellRaisers","player_role":"Mid","kills":3,"deaths":2.4,"creep_score":0.804,"gold_per_min":1.248,"tower_kills":0,"roshan_kills":1,"team_fight":1.9565,"obs_wards_planted":0.5,"camps_stacked":0,"runes_grabbed":4,"first_blood":0,"stuns":1.39,"total":16.2985},{"player_name":"Munkushi~太阳","team_name":"One Move","player_role":"Core","kills":2.55,"deaths":2.15,"creep_score":1.282,"gold_per_min":1.2593,"tower_kills":1.8333,"roshan_kills":0.5,"team_fight":1.7212,"obs_wards_planted":0.0833,"camps_stacked":1,"runes_grabbed":0.4583,"first_blood":0,"stuns":1.3728,"total":14.2103},{"player_name":"Nightfall","team_name":"BetBoom Team","player_role":"Core","kills":"NA","deaths":"NA","creep_score":"NA","gold_per_min":"NA","tower_kills":"NA","roshan_kills":"NA","team_fight":"NA","obs_wards_planted":"NA","camps_stacked":"NA","runes_grabbed":"NA","first_blood":"NA","stuns":"NA","total":"NA"},{"player_name":"Save-","team_name":"BetBoom Team","player_role":"Support","kills":"NA","deaths":"NA","creep_score":"NA","gold_per_min":"NA","tower_kills":"NA","roshan_kills":"NA","team_fight":"NA","obs_wards_planted":"NA","camps_stacked":"NA","runes_grabbed":"NA","first_blood":"NA","stuns":"NA","total":"NA"},{"player_name":"Pure~","team_name":"BetBoom Team","player_role":"Core","kills":"NA","deaths":"NA","creep_score":"NA","gold_per_min":"NA","tower_kills":"NA","roshan_kills":"NA","team_fight":"NA","obs_wards_planted":"NA","camps_stacked":"NA","runes_grabbed":"NA","first_blood":"NA","stuns":"NA","total":"NA"},{"player_name":"TORONTOTOKYO","team_name":"BetBoom Team","player_role":"Support","kills":"NA","deaths":"NA","creep_score":"NA","gold_per_min":"NA","tower_kills":"NA","roshan_kills":"NA","team_fight":"NA","obs_wards_planted":"NA","camps_stacked":"NA","runes_grabbed":"NA","first_blood":"NA","stuns":"NA","total":"NA"},{"player_name":"gpk~","team_name":"BetBoom Team","player_role":"Mid","kills":"NA","deaths":"NA","creep_score":"NA","gold_per_min":"NA","tower_kills":"NA","roshan_kills":"NA","team_fight":"NA","obs_wards_planted":"NA","camps_stacked":"NA","runes_grabbed":"NA","first_blood":"NA","stuns":"NA","total":"NA"}],"result_aggregate":[{"player_name":"mellojul","team_name":"Natus Vincere","player_role":"Mid","1":33.8151,"NA":"NA","total":33.8151},{"player_name":"Worick","team_name":"HYDRA","player_role":"Mid","1":41.5589,"NA":"NA","total":41.5589},{"player_name":"AfterLife","team_name":"One Move","player_role":"Core","1":22.491,"NA":"NA","total":22.491},{"player_name":"Malady","team_name":"Natus Vincere","player_role":"Support","1":25.0822,"NA":"NA","total":25.0822},{"player_name":"Fng","team_name":"Virtus.pro","player_role":"Support","1":5.1696,"NA":"NA","total":5.1696},{"player_name":"Larl","team_name":"Team Spirit","player_role":"Mid","1":26.4857,"NA":"NA","total":26.4857},{"player_name":"pantomem","team_name":"One Move","player_role":"Support","1":31.4347,"NA":"NA","total":31.4347},{"player_name":"Miposhka","team_name":"Team Spirit","player_role":"Support","1":28.8083,"NA":"NA","total":28.8083},{"player_name":"SoNNeikO","team_name":"Darkside","player_role":"Support","1":34.365,"NA":"NA","total":34.365},{"player_name":"squad1x","team_name":"Virtus.pro","player_role":"Mid","1":15.3043,"NA":"NA","total":15.3043},{"player_name":"RAMZES666","team_name":"HellRaisers","player_role":"Core","1":11.6196,"NA":"NA","total":11.6196},{"player_name":"Solo","team_name":"HellRaisers","player_role":"Support","1":9.5312,"NA":"NA","total":9.5312},{"player_name":"Lefitan","team_name":"HYDRA","player_role":"Core","1":22.9013,"NA":"NA","total":22.9013},{"player_name":"sayuw","team_name":"Virtus.pro","player_role":"Support","1":11.1902,"NA":"NA","total":11.1902},{"player_name":"dizzying","team_name":"Darkside","player_role":"Core","1":33.6421,"NA":"NA","total":33.6421},{"player_name":"RodjER","team_name":"Darkside","player_role":"Support","1":33.1415,"NA":"NA","total":33.1415},{"player_name":"Antares","team_name":"HellRaisers","player_role":"Support","1":12.5988,"NA":"NA","total":12.5988},{"player_name":"MieRo`","team_name":"HellRaisers","player_role":"Core","1":15.7086,"NA":"NA","total":15.7086},{"player_name":"Cloud","team_name":"HYDRA","player_role":"Core","1":28.1616,"NA":"NA","total":28.1616},{"player_name":"Kiritych~","team_name":"Virtus.pro","player_role":"Core","1":10.2868,"NA":"NA","total":10.2868},{"player_name":"Gilgir","team_name":"One Move","player_role":"Support","1":29.318,"NA":"NA","total":29.318},{"player_name":"shigetsu","team_name":"Natus Vincere","player_role":"Core","1":37.592,"NA":"NA","total":37.592},{"player_name":"Noticed","team_name":"Virtus.pro","player_role":"Core","1":10.8532,"NA":"NA","total":10.8532},{"player_name":"Ainkrad","team_name":"One Move","player_role":"Mid","1":41.4433,"NA":"NA","total":41.4433},{"player_name":"Malik","team_name":"Natus Vincere","player_role":"Core","1":39.5503,"NA":"NA","total":39.5503},{"player_name":"Blizzy","team_name":"Darkside","player_role":"Core","1":28.9865,"NA":"NA","total":28.9865},{"player_name":"Kami","team_name":"HYDRA","player_role":"Core","1":45.5179,"NA":"NA","total":45.5179},{"player_name":"Mira","team_name":"Team Spirit","player_role":"Support","1":23.2372,"NA":"NA","total":23.2372},{"player_name":"Collapse","team_name":"Team Spirit","player_role":"Core","1":35.6806,"NA":"NA","total":35.6806},{"player_name":"Yatoro雨","team_name":"Team Spirit","player_role":"Core","1":47.4701,"NA":"NA","total":47.4701},{"player_name":"Danial","team_name":"Natus Vincere","player_role":"Support","1":30.3957,"NA":"NA","total":30.3957},{"player_name":"HappyDyurara","team_name":"HYDRA","player_role":"Support","1":33.5729,"NA":"NA","total":33.5729},{"player_name":"reibl","team_name":"Darkside","player_role":"Mid","1":41.305,"NA":"NA","total":41.305},{"player_name":"kiyotaka","team_name":"HellRaisers","player_role":"Mid","1":16.2985,"NA":"NA","total":16.2985},{"player_name":"Munkushi~太阳","team_name":"One Move","player_role":"Core","1":43.7727,"NA":"NA","total":43.7727},{"player_name":"Nightfall","team_name":"BetBoom Team","player_role":"Core","1":"NA","NA":"NA","total":0},{"player_name":"Save-","team_name":"BetBoom Team","player_role":"Support","1":"NA","NA":"NA","total":0},{"player_name":"Pure~","team_name":"BetBoom Team","player_role":"Core","1":"NA","NA":"NA","total":0},{"player_name":"TORONTOTOKYO","team_name":"BetBoom Team","player_role":"Support","1":"NA","NA":"NA","total":0},{"player_name":"gpk~","team_name":"BetBoom Team","player_role":"Mid","1":"NA","NA":"NA","total":0}]}
